Workbook

Sheet About & Rules
A1: Lovely Bites
A3: Fictional business, made up for planning and testing. Not a real company.
A5: Who we are
A7: • Small independent event caterer based in St Saviour, Jersey, trading since 2014
A8: • Run by a husband-and-wife team, a head chef and around 6 core staff, plus a pool of casual servers for busy weekends
A9: • We cook from our own kitchen unit and buy local wherever we can: Jersey Royals, Jersey dairy, island-landed fish and shellfish, local growers for veg
A10: • We cover the whole island, all 12 parishes
A12: Events we do
A14: • Weddings: marquee, barn and hotel-venue receptions, from 40 to 250 guests. Our biggest line of work, May to September
A15: • Corporate: finance and legal firm lunches, client evenings, staff parties and summer dos in St Helier
A16: • Private parties: milestone birthdays, anniversaries and garden parties at home
A17: • Christmas parties: busy November and December, mostly corporate
... A64: • If a requested discount would take the price below that floor, we refuse the discount and explain why, showing the floor price. We can offer something else instead, such as a cheaper menu tier or a buffet instead of seated service

Sheet Menus
A1: Menu prices per head, with guest-number price breaks
A2: Blue = typed-in prices. Black = formulas. Food margin = price minus food cost only; staff, hire and travel still to come off.
A3: Tier | B3: Guests | C3: Price per head (£) | D3: Food cost per head (£) | E3: Food margin per head (£) | F3: Food margin % | G3: Notes
A4: Classic | B4: 1–49 | C4: 34 | D4: ='Food Costs'!$B$4 -> 11.5 | E4: =C4-D4 -> 22.5 | F4: =IF(C4=0,0,E4/C4) -> 0.66176471 | G4: 2 courses
A5: Classic | B5: 50–99 | C5: 31 | D5: ='Food Costs'!$B$4 -> 11.5 | E5: =C5-D5 -> 19.5 | F5: =IF(C5=0,0,E5/C5) -> 0.62903226 | G5: 2 courses
A6: Classic | B6: 100–199 | C6: 28.5 | D6: ='Food Costs'!$B$4 -> 11.5 | E6: =C6-D6 -> 17 | F6: =IF(C6=0,0,E6/C6) -> 0.59649123 | G6: 2 courses
A7: Classic | B7: 200+ | C7: 26.5 | D7: ='Food Costs'!$B$4 -> 11.5 | E7: =C7-D7 -> 15 | F7: =IF(C7=0,0,E7/C7) -> 0.56603774 | G7: 2 courses
A8: Signature | B8: 1–49 | C8: 52 | D8: ='Food Costs'!$B$5 -> 17.75 | E8: =C8-D8 -> 34.25 | F8: =IF(C8=0,0,E8/C8) -> 0.65865385 | G8: 3 courses
A9: Signature | B9: 50–99 | C9: 48 | D9: ='Food Costs'!$B$5 -> 17.75 | E9: =C9-D9 -> 30.25 | F9: =IF(C9=0,0,E9/C9) -> 0.63020833 | G9: 3 courses
A10: Signature | B10: 100–199 | C10: 44.5 | D10: ='Food Costs'!$B$5 -> 17.75 | E10: =C10-D10 -> 26.75 | F10: =IF(C10=0,0,E10/C10) -> 0.6011236 | G10: 3 courses
A11: Signature | B11: 200+ | C11: 41.5 | D11: ='Food Costs'!$B$5 -> 17.75 | E11: =C11-D11 -> 23.75 | F11: =IF(C11=0,0,E11/C11) -> 0.57228916 | G11: 3 courses
A12: Prestige | B12: 1–49 | C12: 82 | D12: ='Food Costs'!$B$6 -> 29 | E12: =C12-D12 -> 53 | F12: =IF(C12=0,0,E12/C12) -> 0.64634146 | G12: 4 courses + amuse-bouche; tasting included
A13: Prestige | B13: 50–99 | C13: 76 | D13: ='Food Costs'!$B$6 -> 29 | E13: =C13-D13 -> 47 | F13: =IF(C13=0,0,E13/C13) -> 0.61842105 | G13: 4 courses + amuse-bouche; tasting included
A14: Prestige | B14: 100–199 | C14: 71 | D14: ='Food Costs'!$B$6 -> 29 | E14: =C14-D14 -> 42 | F14: =IF(C14=0,0,E14/C14) -> 0.5915493 | G14: 4 courses + amuse-bouche; tasting included
A15: Prestige | B15: 200+ | C15: 67 | D15: ='Food Costs'!$B$6 -> 29 | E15: =C15-D15 -> 38 | F15: =IF(C15=0,0,E15/C15) -> 0.56716418 | G15: 4 courses + amuse-bouche; tasting included

Sheet Food Costs
A1: Food cost per head (internal only)
A2: Blue = typed-in figures you can change. Ingredients and consumables only, not staff.
A3: Tier | B3: Food cost per head (£) | C3: Notes
A4: Classic | B4: 11.5 | C4: Ingredients and consumables; internal only
A5: Signature | B5: 17.75 | C5: Ingredients and consumables; internal only
A6: Prestige | B6: 29 | C6: Ingredients and consumables; internal only

Sheet Canapés & Drinks
A1: Canapé and drinks add-ons, and dietary surcharge
A2: Blue = typed-in prices.
A3: Type | B3: Item | C3: Charged | D3: Price (£) | E3: Minimum charge (£) | F3: Notes
A4: Canapes | B4: Canapés (3 per guest) | C4: per head | D4: 7.5 | E4: 150 | F4: Chef's selection
A5: Canapes | B5: Canapés (5 per guest) | C5: per head | D5: 11.5 | E5: 200 | F5: Chef's selection
A6: Canapes | B6: Premium canapés (5 per guest) | C6: per head | D6: 16 | E6: 300 | F6: Includes oysters and local crab
A7: Drinks | B7: Arrival drink (Prosecco or soft) | C7: per head | D7: 6.5 | F7: One glass per guest
A8: Drinks | B8: Wine with meal (half bottle) | C8: per head | D8: 14 | F8: House red/white/rosé
A9: Drinks | B9: Toast drink (Prosecco) | C9: per head | D9: 5.5 | F9: One glass per guest
A10: Drinks | B10: Soft drinks package | C10: per head | D10: 4.5 | F10: Juices and sparkling water through the event
A11: Drinks | B11: Corkage (client's own wine) | C11: per bottle | D11: 8 | F11: Includes glassware and service
A12: Dietary | B12: Dietary surcharge | C12: per head | D12: 4 | F12: Per guest needing a separate dish (e.g. vegan; gluten-free; allergen-safe)

Sheet Equipment Hire
A1: Equipment hire
A2: Blue = typed-in prices. The minimum charge applies when quantity × price comes to less.
A3: Item | B3: Charged | C3: Price (£) | D3: Minimum charge (£) | E3: Notes
A4: Round table (seats 10) | B4: per item | C4: 14 | D4: 70
A5: Trestle table (6ft) | B5: per item | C5: 9 | D5: 45
A6: Banqueting chair | B6: per item | C6: 3.5 | D6: 70
A7: Chair cover and sash | B7: per item | C7: 3 | D7: 60
A8: Linen tablecloth | B8: per item | C8: 8.5 | D8: 40
A9: Linen napkin | B9: per item | C9: 0.85 | D9: 25
A10: Crockery and cutlery set | B10: per head | C10: 3.25 | D10: 60 | E10: Per place setting
A11: Glassware set (3 glasses) | B11: per head | C11: 1.8 | D11: 40 | E11: Per place setting
A12: Mobile bar unit | B12: per event | C12: 180 | D12: 180
A13: Field kitchen (marquee events) | B13: per event | C13: 450 | D13: 450 | E13: Ovens and hot cupboards
A14: Patio heater | B14: per item | C14: 45 | D14: 90 | E14: Includes gas

Sheet Travel by Parish
A1: Travel and setup charge by parish
A2: Blue = typed-in prices. One charge per event.
A3: Parish | B3: Charge per event (£) | C3: Notes
A4: St Helier | B4: 45 | C4: Travel and setup
A5: St Saviour | B5: 35 | C5: Travel and setup; home parish
A6: St Clement | B6: 50 | C6: Travel and setup
A7: Grouville | B7: 55 | C7: Travel and setup
A8: St Martin | B8: 60 | C8: Travel and setup
A9: Trinity | B9: 60 | C9: Travel and setup
A10: St John | B10: 70 | C10: Travel and setup
A11: St Lawrence | B11: 60 | C11: Travel and setup
A12: St Peter | B12: 70 | C12: Travel and setup
A13: St Mary | B13: 75 | C13: Travel and setup
A14: St Brelade | B14: 75 | C14: Travel and setup
A15: St Ouen | B15: 85 | C15: Travel and setup
